scistringparser
