Metadata-Version: 2.1
Name: scistringparser
Version: 0.1.5
Summary: A python module that converts strings in the metric scientific notation to numerical data types.
Home-page: https://github.com/RodrigoMoraes98/PyScientificStringParser
Author: Rodrigo Moraes
Author-email: rodrigo.smoraes98@gmail.com
Classifier: Programming Language :: Python :: 3
Classifier: License :: OSI Approved :: MIT License
Classifier: Operating System :: OS Independent
Requires-Python: >=3.6
License-File: LICENSE
